pypipo/__init__.py
pypipo/__main__.py
pypipo/__version__.py
pypipo/cli.py
pypipo/convert.py
pypipo/libs/__init__.py
pypipo/libs/imageProcessing.py
pypipo/libs/process.py
pypipo/libs/temp.py
pypipo/libs/utils.py
pypipo_py-0.0.6.dist-info/LICENSE
pypipo_py-0.0.6.dist-info/METADATA
pypipo_py-0.0.6.dist-info/WHEEL
pypipo_py-0.0.6.dist-info/entry_points.txt
pypipo_py-0.0.6.dist-info/top_level.txt
pypipo_py-0.0.6.dist-info/RECORD
